peachpayments_partner_marshmallow/__init__.py
peachpayments_partner_marshmallow/fields.py
peachpayments_partner_marshmallow/schemas.py
peachpayments_partner_marshmallow/validate.py
peachpayments_partner_marshmallow/validator.py
peachpayments_partner_marshmallow-1.2.0.dist-info/LICENSE.txt
peachpayments_partner_marshmallow-1.2.0.dist-info/METADATA
peachpayments_partner_marshmallow-1.2.0.dist-info/WHEEL
peachpayments_partner_marshmallow-1.2.0.dist-info/RECORD
